setup.py
article_segment/__init__.py
article_segment/article_segment.py
article_segment.egg-info/PKG-INFO
article_segment.egg-info/SOURCES.txt
article_segment.egg-info/dependency_links.txt
article_segment.egg-info/not-zip-safe
article_segment.egg-info/requires.txt
article_segment.egg-info/top_level.txt