Metadata-Version: 1.1
Name: article-segment
Version: 0.0.1
Summary: article_segment
Home-page: http://github.com/17zuoye/article_segment/
Author: David Chen
Author-email: mvjome@gmail.com
License: MIT
Platform: any
Classifier: Intended Audience :: Developers
Classifier: Operating System :: OS Independent
Classifier: Programming Language :: Python
Classifier: Topic :: Software Development :: Libraries :: Python Modules
